openmeter/__init__.py
openmeter/client.py
openmeter_client-1.0.3.dist-info/METADATA
openmeter_client-1.0.3.dist-info/WHEEL
openmeter_client-1.0.3.dist-info/top_level.txt
openmeter_client-1.0.3.dist-info/RECORD
