Metadata-Version: 2.1
Name: openmeter_client
Version: 1.0.3
Summary: A Python client to interact with the OpenMeter API endpoints
Requires-Dist: requests
Requires-Dist: pandas
Requires-Dist: loguru
